pypersia/calander.py
pypersia/convert.py
pypersia/keyboard.py
pypersia/numbers.py
pypersia/text.py
pypersia-1.5.0.dist-info/licenses/LICENSE.txt
pypersia-1.5.0.dist-info/METADATA
pypersia-1.5.0.dist-info/WHEEL
pypersia-1.5.0.dist-info/top_level.txt
pypersia-1.5.0.dist-info/RECORD
