Metadata-Version: 2.4
Name: pypersia
Version: 1.5.0
Summary: A Python library for Persian utilities
Author-email: Aria Farahmand <aria.farahmand1391@gmail.com>
License-Expression: MIT
Project-URL: Homepage, https://github.com/the-golden-one/pypersia
Project-URL: Issues, https://github.com/the-golden-one/pypersia/issues
Classifier: Programming Language :: Python :: 3
Classifier: Operating System :: OS Independent
Requires-Python: >=3.9
License-File: LICENSE.txt
Dynamic: license-file
